bisectlib.py
bisectlib-0.1.0.dist-info/METADATA
bisectlib-0.1.0.dist-info/WHEEL
bisectlib-0.1.0.dist-info/top_level.txt
bisectlib-0.1.0.dist-info/RECORD
